adropinthebucket/__about__.py
adropinthebucket/__init__.py
adropinthebucket/main.py
adropinthebucket-0.0.1.dist-info/METADATA
adropinthebucket-0.0.1.dist-info/WHEEL
adropinthebucket-0.0.1.dist-info/licenses/LICENSE.txt
adropinthebucket-0.0.1.dist-info/RECORD
